json_to_toon_converter/__init__.py
json_to_toon_converter/converter.py
json_to_toon_converter/utils.py
json_toon_converter-0.1.2.dist-info/LICENSE
json_toon_converter-0.1.2.dist-info/METADATA
json_toon_converter-0.1.2.dist-info/WHEEL
json_toon_converter-0.1.2.dist-info/entry_points.txt
json_toon_converter-0.1.2.dist-info/top_level.txt
json_toon_converter-0.1.2.dist-info/RECORD
