Metadata-Version: 2.1
Name: json-toon-converter
Version: 0.1.2
Summary: A package to convert JSON to TOON and TOON to JSON
Home-page: https://github.com/OrenGrinker/json-toon-converter
Author: Oren Grinker
Author-email: orengr4@gmail.com
License: UNKNOWN
Platform: UNKNOWN
Classifier: Programming Language :: Python :: 3
Classifier: License :: OSI Approved :: MIT License
Classifier: Operating System :: OS Independent
Requires-Dist: toon-python
